corelated_logs/__init__.py
corelated_logs/constants.py
corelated_logs/django_corelation_middleware.py
corelated_logs/flask_corelation_middleware.py
corelated_logs/patcher.py
corelated_logs/ext/__init__.py
corelated_logs/ext/kombu/__init__.py
corelated_logs/ext/kombu/patch.py
corelated_logs/ext/requests/__init__.py
corelated_logs/ext/requests/patch.py
tests/ext/__init__.py
tests/ext/test_request.py
corelated_logs-0.1.0.dist-info/LICENSE
corelated_logs-0.1.0.dist-info/METADATA
corelated_logs-0.1.0.dist-info/WHEEL
corelated_logs-0.1.0.dist-info/top_level.txt
corelated_logs-0.1.0.dist-info/RECORD
